{
  "name": "a8af2963-87e7-4073-9c78-cdee679f0c1f",
  "tags": [ "#nomatch#symptoms" ],
  "displayName": "Error Handling - three no matches at symptoms page",
  "testCaseConversationTurns": [ {
    "userInput": {
      "isWebhookEnabled": true,
      "input": {
        "text": {
          "text": "I am not feeling well"
        },
        "languageCode": "en"
      }
    },
    "virtualAgentOutput": {
      "triggeredIntent": {
        "name": "healthcare.symptoms"
      },
      "currentPage": {
        "name": "Symptoms",
        "flow": "Default Start Flow"
      },
      "textResponses": [ {
        "text": [ "Apologies I can't address your symptoms but I can assist you to find a doctor, would you like help with this?\n\nPlease note, if this is a medical emergency, go to your local emergency room." ]
      } ],
      "currentFlow": {
        "name": "Default Start Flow"
      }
    }
  }, {
    "userInput": {
      "isWebhookEnabled": true,
      "input": {
        "text": {
          "text": "dcaczcz"
        },
        "languageCode": "en"
      }
    },
    "virtualAgentOutput": {
      "currentPage": {
        "name": "Symptoms",
        "flow": "Default Start Flow"
      },
      "textResponses": [ {
        "text": [ "Apologies, I cannot answer that. I can assist you to find a doctor, would you like help with this? " ]
      } ],
      "currentFlow": {
        "name": "Default Start Flow"
      }
    }
  }, {
    "userInput": {
      "isWebhookEnabled": true,
      "input": {
        "text": {
          "text": "adczsc"
        },
        "languageCode": "en"
      }
    },
    "virtualAgentOutput": {
      "currentPage": {
        "name": "Symptoms",
        "flow": "Default Start Flow"
      },
      "textResponses": [ {
        "text": [ "Sorry, I did not understand that. Do you want me to help you find a doctor?" ]
      } ],
      "currentFlow": {
        "name": "Default Start Flow"
      }
    }
  }, {
    "userInput": {
      "isWebhookEnabled": true,
      "input": {
        "text": {
          "text": "acac"
        },
        "languageCode": "en"
      }
    },
    "virtualAgentOutput": {
      "currentPage": {
        "name": "End Session",
        "flow": "Default Start Flow"
      },
      "textResponses": [ {
        "text": [ "Apologies, a customer service representative will be better able to help you. Let me transfer your call. Thank you for your patience." ]
      } ],
      "currentFlow": {
        "name": "Default Start Flow"
      }
    }
  } ],
  "creationTime": {
    "seconds": 1607088886,
    "nanos": 408004000
  }
}
